[{"time":0.0,"pose":{"rotation":{"radians":0.0},"translation":{"x":2.32,"y":3.0}},"velocity":0,"acceleration":3.0,"curvature":0,"holonomicRotation":180.0,"angularVelocity":0.0,"holonomicAngularVelocity":0.0},{"time":0.08961738878885948,"pose":{"rotation":{"radians":0.0},"translation":{"x":2.3320469145600002,"y":3.0}},"velocity":0.2688521663665785,"acceleration":3.0000000000000004,"curvature":0,"holonomicRotation":180.0,"angularVelocity":0.0,"holonomicAngularVelocity":0.0},{"time":0.12698334924968188,"pose":{"rotation":{"radians":0.0},"translation":{"x":2.34418715648,"y":3.0}},"velocity":0.3809500477490457,"acceleration":2.9999999999999996,"curvature":0,"holonomicRotation":180.0,"angularVelocity":0.0,"holonomicAngularVelocity":0.0},{"time":0.15582035194415322,"pose":{"rotation":{"radians":0.0},"translation":{"x":2.3564199731199995,"y":3.0}},"velocity":0.4674610558324597,"acceleration":3.000000000000001,"curvature":0,"holonomicRotation":180.0,"angularVelocity":0.0,"holonomicAngularVelocity":0.0},{"time":0.18026760078653375,"pose":{"rotation":{"radians":0.0},"translation":{"x":2.3687446118399995,"y":3.0}},"velocity":0.5408028023596013,"acceleration":3.0,"curvature":0,"holonomicRotation":180.0,"angularVelocity":0.0,"holonomicAngularVelocity":0.0},{"time":0.2019246063922545,"pose":{"rotation":{"radians":0.0},"translation":{"x":2.38116032,"y":3.0}},"velocity":0.6057738191767635,"acceleration":2.9999999999999973,"curvature":0,"holonomicRotation":180.0,"angularVelocity":0.0,"holonomicAngularVelocity":0.0},{"time":0.22160978462152778,"pose":{"rotation":{"radians":0.0},"translation":{"x":2.3936663449599997,"y":3.0}},"velocity":0.6648293538645833,"acceleration":2.9999999999999987,"curvature":0,"holonomicRotation":180.0,"angularVelocity":0.0,"holonomicAngularVelocity":0.0},{"time":0.23980816510980935,"pose":{"rotation":{"radians":0.0},"translation":{"x":2.40626193408,"y":3.0}},"velocity":0.719424495329428,"acceleration":2.9999999999999987,"curvature":0,"holonomicRotation":180.0,"angularVelocity":0.0,"holonomicAngularVelocity":1.6692292120391615e-12},{"time":0.25683501152815325,"pose":{"rotation":{"radians":0.0},"translation":{"x":2.4189463347199998,"y":3.0}},"velocity":0.7705050345844596,"acceleration":2.999999999999997,"curvature":0,"holonomicRotation":180.00000000000003,"angularVelocity":0.0,"holonomicAngularVelocity":-1.7682056980365508e-12},{"time":0.27290876893203675,"pose":{"rotation":{"radians":0.0},"translation":{"x":2.4317187942399996,"y":3.0}},"velocity":0.8187263067961101,"acceleration":3.0,"curvature":0,"holonomicRotation":180.0,"angularVelocity":0.0,"holonomicAngularVelocity":0.0},{"time":0.288188086730408,"pose":{"rotation":{"radians":0.0},"translation":{"x":2.4445785599999996,"y":3.0}},"velocity":0.864564260191224,"acceleration":3.0000000000000036,"curvature":0,"holonomicRotation":180.0,"angularVelocity":0.0,"holonomicAngularVelocity":0.0},{"time":0.3027924254446714,"pose":{"rotation":{"radians":0.0},"translation":{"x":2.45752487936,"y":3.0}},"velocity":0.9083772763340141,"acceleration":3.0,"curvature":0,"holonomicRotation":180.0,"angularVelocity":0.0,"holonomicAngularVelocity":0.0},{"time":0.31681435119009366,"pose":{"rotation":{"radians":0.0},"translation":{"x":2.47055699968,"y":3.0}},"velocity":0.9504430535702809,"acceleration":3.0,"curvature":0,"holonomicRotation":180.0,"angularVelocity":0.0,"holonomicAngularVelocity":0.0},{"time":0.330327280455813,"pose":{"rotation":{"radians":0.0},"translation":{"x":2.48367416832,"y":3.0}},"velocity":0.9909818413674389,"acceleration":3.0,"curvature":0,"holonomicRotation":180.0,"angularVelocity":0.0,"holonomicAngularVelocity":2.175691959707903e-12},{"time":0.34339057707902604,"pose":{"rotation":{"radians":0.0},"translation":{"x":2.4968756326399997,"y":3.0}},"velocity":1.030171731237078,"acceleration":2.9999999999999916,"curvature":0,"holonomicRotation":180.00000000000003,"angularVelocity":0.0,"holonomicAngularVelocity":-2.2445658949731007e-12},{"time":0.35605302975820863,"pose":{"rotation":{"radians":0.0},"translation":{"x":2.5101606399999996,"y":3.0}},"velocity":1.0681590892746258,"acceleration":3.0000000000000044,"curvature":0,"holonomicRotation":180.0,"angularVelocity":0.0,"holonomicAngularVelocity":0.0},{"time":0.36835529746880674,"pose":{"rotation":{"radians":0.0},"translation":{"x":2.5235284377599996,"y":3.0}},"velocity":1.10506589240642,"acceleration":2.9999999999999956,"curvature":0,"holonomicRotation":180.0,"angularVelocity":0.0,"holonomicAngularVelocity":0.0},{"time":0.3803316739198389,"pose":{"rotation":{"radians":0.0},"translation":{"x":2.53697827328,"y":3.0}},"velocity":1.1409950217595166,"acceleration":3.0000000000000044,"curvature":0,"holonomicRotation":180.0,"angularVelocity":0.0,"holonomicAngularVelocity":0.0},{"time":0.39201138922230283,"pose":{"rotation":{"radians":0.0},"translation":{"x":2.5505093939199996,"y":3.0}},"velocity":1.1760341676669084,"acceleration":3.0,"curvature":0,"holonomicRotation":180.0,"angularVelocity":0.0,"holonomicAngularVelocity":-2.491340463825484e-12},{"time":0.40341958888151846,"pose":{"rotation":{"radians":0.0},"translation":{"x":2.56412104704,"y":3.0}},"velocity":1.2102587666445552,"acceleration":2.999999999999995,"curvature":0,"holonomicRotation":179.99999999999997,"angularVelocity":0.0,"holonomicAngularVelocity":2.547091915588987e-12},{"time":0.4145780827138197,"pose":{"rotation":{"radians":0.0},"translation":{"x":2.57781248,"y":3.0}},"velocity":1.2437342481414588,"acceleration":2.999999999999995,"curvature":0,"holonomicRotation":180.0,"angularVelocity":0.0,"holonomicAngularVelocity":0.0},{"time":0.4255059264452142,"pose":{"rotation":{"radians":0.0},"translation":{"x":2.59158294016,"y":3.0}},"velocity":1.2765177793356424,"acceleration":3.000000000000005,"curvature":0,"holonomicRotation":180.0,"angularVelocity":0.0,"holonomicAngularVelocity":0.0},{"time":0.43621987947975677,"pose":{"rotation":{"radians":0.0},"translation":{"x":2.60543167488,"y":3.0}},"velocity":1.3086596384392701,"acceleration":3.0,"curvature":0,"holonomicRotation":180.0,"angularVelocity":0.0,"holonomicAngularVelocity":0.0},{"time":0.44673476957437125,"pose":{"rotation":{"radians":0.0},"translation":{"x":2.6193579315199997,"y":3.0}},"velocity":1.3402043087231135,"acceleration":2.9999999999999893,"curvature":0,"holonomicRotation":180.0,"angularVelocity":0.0,"holonomicAngularVelocity":2.7516374059499448e-12},{"time":0.4570637865331271,"pose":{"rotation":{"radians":0.0},"translation":{"x":2.63336095744,"y":3.0}},"velocity":1.3711913595993812,"acceleration":3.0000000000000107,"curvature":0,"holonomicRotation":180.00000000000003,"angularVelocity":0.0,"holonomicAngularVelocity":-2.798807740427632e-12},{"time":0.4672187210861027,"pose":{"rotation":{"radians":0.0},"translation":{"x":2.64744,"y":3.0}},"velocity":1.401656163258308,"acceleration":3.000000000000011,"curvature":0,"holonomicRotation":180.0,"angularVelocity":0.0,"holonomicAngularVelocity":-2.844605966626931e-12},{"time":0.47721016094239527,"pose":{"rotation":{"radians":0.0},"translation":{"x":2.66159430656,"y":3.0}},"velocity":1.4316304828271857,"acceleration":3.0,"curvature":0,"holonomicRotation":179.99999999999997,"angularVelocity":0.0,"holonomicAngularVelocity":0.0},{"time":0.48704765302791475,"pose":{"rotation":{"radians":0.0},"translation":{"x":2.67582312448,"y":3.0}},"velocity":1.4611429590837441,"acceleration":2.9999999999999942,"curvature":0,"holonomicRotation":179.99999999999997,"angularVelocity":0.0,"holonomicAngularVelocity":5.864870981649894e-12},{"time":0.49673983876203587,"pose":{"rotation":{"radians":0.0},"translation":{"x":2.69012570112,"y":3.0}},"velocity":1.4902195162861074,"acceleration":2.9999999999999885,"curvature":0,"holonomicRotation":180.00000000000003,"angularVelocity":0.0,"holonomicAngularVelocity":-2.9746222817040377e-12},{"time":0.5062945676448312,"pose":{"rotation":{"radians":0.0},"translation":{"x":2.7045012838399995,"y":3.0}},"velocity":1.518883702934493,"acceleration":2.999999999999977,"curvature":0,"holonomicRotation":180.0,"angularVelocity":0.0,"holonomicAngularVelocity":0.0},{"time":0.5157189932511699,"pose":{"rotation":{"radians":0.0},"translation":{"x":2.71894912,"y":3.0}},"velocity":1.547156979753509,"acceleration":2.9999999999999765,"curvature":0,"holonomicRotation":180.0,"angularVelocity":0.0,"holonomicAngularVelocity":0.0},{"time":0.5250196548447817,"pose":{"rotation":{"radians":0.0},"translation":{"x":2.7334684569600003,"y":3.0}},"velocity":1.5750589645343445,"acceleration":2.999999999999988,"curvature":0,"holonomicRotation":180.0,"angularVelocity":0.0,"holonomicAngularVelocity":0.0},{"time":0.5342025471547911,"pose":{"rotation":{"radians":0.0},"translation":{"x":2.74805854208,"y":3.0}},"velocity":1.6026076414643726,"acceleration":3.000000000000012,"curvature":0,"holonomicRotation":180.0,"angularVelocity":0.0,"holonomicAngularVelocity":0.0},{"time":0.543273180343002,"pose":{"rotation":{"radians":0.0},"translation":{"x":2.7627186227199996,"y":3.0}},"velocity":1.629819541029005,"acceleration":2.9999999999999756,"curvature":0,"holonomicRotation":180.0,"angularVelocity":0.0,"holonomicAngularVelocity":0.0},{"time":0.5522366317923263,"pose":{"rotation":{"radians":0.0},"translation":{"x":2.7774479462399997,"y":3.0}},"velocity":1.6567098953769779,"acceleration":2.9999999999999876,"curvature":0,"holonomicRotation":180.0,"angularVelocity":0.0,"holonomicAngularVelocity":0.0},{"time":0.5610975910362359,"pose":{"rotation":{"radians":0.0},"translation":{"x":2.79224576,"y":3.0}},"velocity":1.6832927731087066,"acceleration":2.9999999999999876,"curvature":0,"holonomicRotation":180.0,"angularVelocity":0.0,"holonomicAngularVelocity":0.0},{"time":0.5698603989048548,"pose":{"rotation":{"radians":0.0},"translation":{"x":2.80711131136,"y":3.0}},"velocity":1.7095811967145633,"acceleration":2.999999999999987,"curvature":0,"holonomicRotation":180.0,"angularVelocity":0.0,"holonomicAngularVelocity":0.0},{"time":0.5785290817697357,"pose":{"rotation":{"radians":0.0},"translation":{"x":2.82204384768,"y":3.0}},"velocity":1.7355872453092058,"acceleration":2.999999999999987,"curvature":0,"holonomicRotation":180.0,"angularVelocity":0.0,"holonomicAngularVelocity":0.0},{"time":0.5871073816148685,"pose":{"rotation":{"radians":0.0},"translation":{"x":2.8370426163199998,"y":3.0}},"velocity":1.7613221448446041,"acceleration":2.999999999999987,"curvature":0,"holonomicRotation":180.0,"angularVelocity":0.0,"holonomicAngularVelocity":0.0},{"time":0.5955987825373725,"pose":{"rotation":{"radians":0.0},"translation":{"x":2.85210686464,"y":3.0}},"velocity":1.7867963476121163,"acceleration":3.000000000000013,"curvature":0,"holonomicRotation":180.0,"angularVelocity":0.0,"holonomicAngularVelocity":0.0},{"time":0.6040065341809917,"pose":{"rotation":{"radians":0.0},"translation":{"x":2.8672358399999998,"y":3.0}},"velocity":1.8120196025429738,"acceleration":3.0,"curvature":0,"holonomicRotation":180.0,"angularVelocity":0.0,"holonomicAngularVelocity":0.0},{"time":0.612333672523949,"pose":{"rotation":{"radians":0.0},"translation":{"x":2.8824287897599996,"y":3.0}},"velocity":1.8370010175718456,"acceleration":3.0,"curvature":0,"holonomicRotation":180.0,"angularVelocity":0.0,"holonomicAngularVelocity":0.0},{"time":0.6205830383760098,"pose":{"rotation":{"radians":0.0},"translation":{"x":2.8976849612799995,"y":3.0}},"velocity":1.861749115128028,"acceleration":3.0,"curvature":0,"holonomicRotation":180.0,"angularVelocity":0.0,"holonomicAngularVelocity":0.0},{"time":0.6287572938847975,"pose":{"rotation":{"radians":0.0},"translation":{"x":2.91300360192,"y":3.0}},"velocity":1.886271881654391,"acceleration":2.9999999999999862,"curvature":0,"holonomicRotation":180.0,"angularVelocity":0.0,"holonomicAngularVelocity":0.0},{"time":0.6368589373061092,"pose":{"rotation":{"radians":0.0},"translation":{"x":2.9283839590399996,"y":3.0}},"velocity":1.9105768119183262,"acceleration":3.0,"curvature":0,"holonomicRotation":180.0,"angularVelocity":0.0,"holonomicAngularVelocity":0.0},{"time":0.6448903162554079,"pose":{"rotation":{"radians":0.0},"translation":{"x":2.9438252799999995,"y":3.0}},"velocity":1.9346709487662224,"acceleration":3.0,"curvature":0,"holonomicRotation":180.0,"angularVelocity":0.0,"holonomicAngularVelocity":0.0},{"time":0.6528536396263204,"pose":{"rotation":{"radians":0.0},"translation":{"x":2.9593268121599996,"y":3.0}},"velocity":1.9585609188789599,"acceleration":3.000000000000028,"curvature":0,"holonomicRotation":180.0,"angularVelocity":0.0,"holonomicAngularVelocity":0.0},{"time":0.6607509883357472,"pose":{"rotation":{"radians":0.0},"translation":{"x":2.9748878028799997,"y":3.0}},"velocity":1.9822529650072405,"acceleration":3.000000000000014,"curvature":0,"holonomicRotation":180.0,"angularVelocity":0.0,"holonomicAngularVelocity":3.6283017733574968e-12},{"time":0.6685843250331255,"pose":{"rotation":{"radians":0.0},"translation":{"x":2.9905074995199996,"y":3.0}},"velocity":2.0057529750993757,"acceleration":3.0000000000000426,"curvature":0,"holonomicRotation":180.00000000000003,"angularVelocity":0.0,"holonomicAngularVelocity":-7.314646490847289e-12},{"time":0.6763555028927712,"pose":{"rotation":{"radians":0.0},"translation":{"x":3.00618514944,"y":3.0}},"velocity":2.029066508678313,"acceleration":3.000000000000014,"curvature":0,"holonomicRotation":179.99999999999997,"angularVelocity":0.0,"holonomicAngularVelocity":3.6859751816470154e-12},{"time":0.6840662735924546,"pose":{"rotation":{"radians":0.0},"translation":{"x":3.02192,"y":3.0}},"velocity":2.0521988207773636,"acceleration":3.000000000000043,"curvature":0,"holonomicRotation":180.0,"angularVelocity":0.0,"holonomicAngularVelocity":0.0},{"time":0.6917182945679551,"pose":{"rotation":{"radians":0.0},"translation":{"x":3.03771129856,"y":3.0}},"velocity":2.075154883703865,"acceleration":3.000000000000029,"curvature":0,"holonomicRotation":180.0,"angularVelocity":0.0,"holonomicAngularVelocity":3.7422388735366615e-12},{"time":0.6993131356218998,"pose":{"rotation":{"radians":0.0},"translation":{"x":3.05355829248,"y":3.0}},"velocity":2.097939406865699,"acceleration":2.9999999999999853,"curvature":0,"holonomicRotation":180.00000000000003,"angularVelocity":0.0,"holonomicAngularVelocity":-3.76988280416744e-12},{"time":0.7068522849553976,"pose":{"rotation":{"radians":0.0},"translation":{"x":3.0694602291199997,"y":3.0}},"velocity":2.120556854866193,"acceleration":3.000000000000044,"curvature":0,"holonomicRotation":180.0,"angularVelocity":0.0,"holonomicAngularVelocity":0.0},{"time":0.7143371546825772,"pose":{"rotation":{"radians":0.0},"translation":{"x":3.08541635584,"y":3.0}},"velocity":2.143011464047732,"acceleration":3.0000000000000147,"curvature":0,"holonomicRotation":180.0,"angularVelocity":0.0,"holonomicAngularVelocity":3.824269718328719e-12},{"time":0.7217690858808884,"pose":{"rotation":{"radians":0.0},"translation":{"x":3.1014259199999996,"y":3.0}},"velocity":2.1653072576426653,"acceleration":2.999999999999985,"curvature":0,"holonomicRotation":180.00000000000003,"angularVelocity":0.0,"holonomicAngularVelocity":-3.851040634422549e-12},{"time":0.7291493532237869,"pose":{"rotation":{"radians":0.0},"translation":{"x":3.11748816896,"y":3.0}},"velocity":2.187448059671361,"acceleration":3.000000000000015,"curvature":0,"holonomicRotation":180.0,"angularVelocity":0.0,"holonomicAngularVelocity":0.0},{"time":0.7364791692369855,"pose":{"rotation":{"radians":0.0},"translation":{"x":3.1336023500800003,"y":3.0}},"velocity":2.2094375077109567,"acceleration":2.999999999999985,"curvature":0,"holonomicRotation":180.0,"angularVelocity":0.0,"holonomicAngularVelocity":0.0},{"time":0.743759688214771,"pose":{"rotation":{"radians":0.0},"translation":{"x":3.14976771072,"y":3.0}},"velocity":2.2312790646443132,"acceleration":3.000000000000015,"curvature":0,"holonomicRotation":180.0,"angularVelocity":0.0,"holonomicAngularVelocity":0.0},{"time":0.7509920098287775,"pose":{"rotation":{"radians":0.0},"translation":{"x":3.1659834982399997,"y":3.0}},"velocity":2.2529760294863324,"acceleration":2.9999999999999694,"curvature":0,"holonomicRotation":180.0,"angularVelocity":0.0,"holonomicAngularVelocity":0.0},{"time":0.7581771824580321,"pose":{"rotation":{"radians":0.0},"translation":{"x":3.18224896,"y":3.0}},"velocity":2.2745315473740964,"acceleration":3.0,"curvature":0,"holonomicRotation":180.0,"angularVelocity":0.0,"holonomicAngularVelocity":0.0},{"time":0.7653162062659679,"pose":{"rotation":{"radians":0.0},"translation":{"x":3.19856334336,"y":3.0}},"velocity":2.2959486187979037,"acceleration":3.0000000000000155,"curvature":0,"holonomicRotation":180.0,"angularVelocity":0.0,"holonomicAngularVelocity":0.0},{"time":0.7724100360473488,"pose":{"rotation":{"radians":0.0},"translation":{"x":3.21492589568,"y":3.0}},"velocity":2.3172301081420468,"acceleration":3.000000000000031,"curvature":0,"holonomicRotation":180.0,"angularVelocity":0.0,"holonomicAngularVelocity":0.0},{"time":0.779459583865642,"pose":{"rotation":{"radians":0.0},"translation":{"x":3.2313358643199996,"y":3.0}},"velocity":2.3383787515969265,"acceleration":3.000000000000047,"curvature":0,"holonomicRotation":180.0,"angularVelocity":0.0,"holonomicAngularVelocity":0.0},{"time":0.7864657214992483,"pose":{"rotation":{"radians":0.0},"translation":{"x":3.24779249664,"y":3.0}},"velocity":2.3593971644977456,"acceleration":3.0,"curvature":0,"holonomicRotation":180.0,"angularVelocity":0.0,"holonomicAngularVelocity":0.0},{"time":0.7934292827131266,"pose":{"rotation":{"radians":0.0},"translation":{"x":3.26429504,"y":3.0}},"velocity":2.3802878481393805,"acceleration":3.0,"curvature":0,"holonomicRotation":180.0,"angularVelocity":0.0,"holonomicAngularVelocity":0.0},{"time":0.8003510653706909,"pose":{"rotation":{"radians":0.0},"translation":{"x":3.28084274176,"y":3.0}},"velocity":2.4010531961120734,"acceleration":3.0,"curvature":0,"holonomicRotation":180.0,"angularVelocity":0.0,"holonomicAngularVelocity":0.0},{"time":0.8072318333993855,"pose":{"rotation":{"radians":0.0},"translation":{"x":3.29743484928,"y":3.0}},"velocity":2.4216955001981573,"acceleration":3.0,"curvature":0,"holonomicRotation":180.0,"angularVelocity":0.0,"holonomicAngularVelocity":0.0},{"time":0.8140723186220414,"pose":{"rotation":{"radians":0.0},"translation":{"x":3.31407060992,"y":3.0}},"velocity":2.442216955866125,"acceleration":3.0000000000000164,"curvature":0,"holonomicRotation":180.0,"angularVelocity":0.0,"holonomicAngularVelocity":4.179107672580563e-12},{"time":0.8208732224649553,"pose":{"rotation":{"radians":0.0},"translation":{"x":3.33074927104,"y":3.0}},"velocity":2.462619667394867,"acceleration":3.000000000000049,"curvature":0,"holonomicRotation":180.00000000000003,"angularVelocity":0.0,"holonomicAngularVelocity":-4.203154403698308e-12},{"time":0.8276352175525962,"pose":{"rotation":{"radians":0.0},"translation":{"x":3.34747008,"y":3.0}},"velocity":2.4829056526577897,"acceleration":3.0000000000000164,"curvature":0,"holonomicRotation":180.0,"angularVelocity":0.0,"holonomicAngularVelocity":0.0},{"time":0.8343589491979255,"pose":{"rotation":{"radians":0.0},"translation":{"x":3.36423228416,"y":3.0}},"velocity":2.503076847593778,"acceleration":3.0000000000000164,"curvature":0,"holonomicRotation":180.0,"angularVelocity":0.0,"holonomicAngularVelocity":0.0},{"time":0.8410450367964845,"pose":{"rotation":{"radians":0.0},"translation":{"x":3.38103513088,"y":3.0}},"velocity":2.5231351103894544,"acceleration":2.9999999999999503,"curvature":0,"holonomicRotation":180.0,"angularVelocity":0.0,"holonomicAngularVelocity":0.0},{"time":0.8476940751316677,"pose":{"rotation":{"radians":0.0},"translation":{"x":3.3978778675200005,"y":3.0}},"velocity":2.5430822253950045,"acceleration":3.00000000000005,"curvature":0,"holonomicRotation":180.0,"angularVelocity":0.0,"holonomicAngularVelocity":-4.298139816699234e-12},{"time":0.8543066355979372,"pose":{"rotation":{"radians":0.0},"translation":{"x":3.41475974144,"y":3.0}},"velocity":2.562919906793813,"acceleration":3.0,"curvature":0,"holonomicRotation":179.99999999999997,"angularVelocity":0.0,"holonomicAngularVelocity":4.321620931497407e-12},{"time":0.8608832673481347,"pose":{"rotation":{"radians":0.0},"translation":{"x":3.43168,"y":3.0}},"velocity":2.582649802044405,"acceleration":2.9999999999999494,"curvature":0,"holonomicRotation":180.0,"angularVelocity":0.0,"holonomicAngularVelocity":0.0},{"time":0.8674244983705114,"pose":{"rotation":{"radians":0.0},"translation":{"x":3.44863789056,"y":3.0}},"velocity":2.602273495111535,"acceleration":3.0,"curvature":0,"holonomicRotation":180.0,"angularVelocity":0.0,"holonomicAngularVelocity":0.0},{"time":0.8739308365006162,"pose":{"rotation":{"radians":0.0},"translation":{"x":3.4656326604800003,"y":3.0}},"velocity":2.6217925095018497,"acceleration":3.000000000000017,"curvature":0,"holonomicRotation":180.0,"angularVelocity":0.0,"holonomicAngularVelocity":-4.391532730705389e-12},{"time":0.8804027703727426,"pose":{"rotation":{"radians":0.0},"translation":{"x":3.4826635571200004,"y":3.0}},"velocity":2.641208311118229,"acceleration":3.000000000000034,"curvature":0,"holonomicRotation":179.99999999999997,"angularVelocity":0.0,"holonomicAngularVelocity":4.414679975807148e-12},{"time":0.886840770315243,"pose":{"rotation":{"radians":0.0},"translation":{"x":3.4997298278400004,"y":3.0}},"velocity":2.6605223109457303,"acceleration":3.0,"curvature":0,"holonomicRotation":180.0,"angularVelocity":0.0,"holonomicAngularVelocity":4.4377587091171386e-12},{"time":0.8932452891936609,"pose":{"rotation":{"radians":0.0},"translation":{"x":3.51683072,"y":3.0}},"velocity":2.679735867580984,"acceleration":3.0,"curvature":0,"holonomicRotation":180.00000000000003,"angularVelocity":0.0,"holonomicAngularVelocity":-4.46077459916445e-12},{"time":0.8996167632053107,"pose":{"rotation":{"radians":0.0},"translation":{"x":3.53396548096,"y":3.0}},"velocity":2.698850289615933,"acceleration":2.9999999999999654,"curvature":0,"holonomicRotation":180.0,"angularVelocity":0.0,"holonomicAngularVelocity":0.0},{"time":0.9059556126286396,"pose":{"rotation":{"radians":0.0},"translation":{"x":3.5511333580800004,"y":3.0}},"velocity":2.7178668378859197,"acceleration":2.9999999999999827,"curvature":0,"holonomicRotation":180.0,"angularVelocity":0.0,"holonomicAngularVelocity":0.0},{"time":0.9122622425304397,"pose":{"rotation":{"radians":0.0},"translation":{"x":3.56833359872,"y":3.0}},"velocity":2.73678672759132,"acceleration":2.999999999999965,"curvature":0,"holonomicRotation":180.0,"angularVelocity":0.0,"holonomicAngularVelocity":0.0},{"time":0.9185370434337423,"pose":{"rotation":{"radians":0.0},"translation":{"x":3.5855654502400007,"y":3.0}},"velocity":2.7556111303012276,"acceleration":2.9999999999999822,"curvature":0,"holonomicRotation":180.0,"angularVelocity":0.0,"holonomicAngularVelocity":0.0},{"time":0.9247803919489932,"pose":{"rotation":{"radians":0.0},"translation":{"x":3.60282816,"y":3.0}},"velocity":2.7743411758469803,"acceleration":3.0,"curvature":0,"holonomicRotation":180.0,"angularVelocity":0.0,"holonomicAngularVelocity":0.0},{"time":0.9309926513709262,"pose":{"rotation":{"radians":0.0},"translation":{"x":3.6201209753600003,"y":3.0}},"velocity":2.7929779541127795,"acceleration":3.0000000000000178,"curvature":0,"holonomicRotation":180.0,"angularVelocity":0.0,"holonomicAngularVelocity":0.0},{"time":0.9371741722433459,"pose":{"rotation":{"radians":0.0},"translation":{"x":3.6374431436800005,"y":3.0}},"velocity":2.8115225167300384,"acceleration":3.0,"curvature":0,"holonomicRotation":180.0,"angularVelocity":0.0,"holonomicAngularVelocity":0.0},{"time":0.943325292893885,"pose":{"rotation":{"radians":0.0},"translation":{"x":3.6547939123200006,"y":3.0}},"velocity":2.8299758786816556,"acceleration":2.999999999999964,"curvature":0,"holonomicRotation":180.0,"angularVelocity":0.0,"holonomicAngularVelocity":0.0},{"time":0.9494463399406347,"pose":{"rotation":{"radians":0.0},"translation":{"x":3.6721725286400004,"y":3.0}},"velocity":2.8483390198219043,"acceleration":2.9999999999999636,"curvature":0,"holonomicRotation":180.0,"angularVelocity":0.0,"holonomicAngularVelocity":0.0},{"time":0.9555376287724102,"pose":{"rotation":{"radians":0.0},"translation":{"x":3.6895782400000003,"y":3.0}},"velocity":2.866612886317231,"acceleration":3.000000000000018,"curvature":0,"holonomicRotation":180.0,"angularVelocity":0.0,"holonomicAngularVelocity":0.0},{"time":0.961599464004288,"pose":{"rotation":{"radians":0.0},"translation":{"x":3.7070102937600007,"y":3.0}},"velocity":2.8847983920128644,"acceleration":3.0,"curvature":0,"holonomicRotation":180.0,"angularVelocity":0.0,"holonomicAngularVelocity":0.0},{"time":0.9676321399099285,"pose":{"rotation":{"radians":0.0},"translation":{"x":3.724467937280001,"y":3.0}},"velocity":2.9028964197297857,"acceleration":2.999999999999982,"curvature":0,"holonomicRotation":180.0,"angularVelocity":0.0,"holonomicAngularVelocity":0.0},{"time":0.9736359408320957,"pose":{"rotation":{"radians":0.0},"translation":{"x":3.74195041792,"y":3.0}},"velocity":2.9209078224962877,"acceleration":3.000000000000037,"curvature":0,"holonomicRotation":180.0,"angularVelocity":0.0,"holonomicAngularVelocity":0.0},{"time":0.9796111415726824,"pose":{"rotation":{"radians":0.0},"translation":{"x":3.7594569830400006,"y":3.0}},"velocity":2.9388334247180476,"acceleration":3.0,"curvature":0,"holonomicRotation":180.0,"angularVelocity":0.0,"holonomicAngularVelocity":0.0},{"time":0.9855580077634535,"pose":{"rotation":{"radians":0.0},"translation":{"x":3.776986880000001,"y":3.0}},"velocity":2.956674023290361,"acceleration":3.0000000000000373,"curvature":0,"holonomicRotation":180.0,"angularVelocity":0.0,"holonomicAngularVelocity":0.0},{"time":0.991476796218651,"pose":{"rotation":{"radians":0.0},"translation":{"x":3.7945393561600005,"y":3.0}},"velocity":2.974430388655954,"acceleration":3.0000000000000187,"curvature":0,"holonomicRotation":180.0,"angularVelocity":0.0,"holonomicAngularVelocity":0.0},{"time":0.9973677552705089,"pose":{"rotation":{"radians":0.0},"translation":{"x":3.8121136588800004,"y":3.0}},"velocity":2.9921032658115276,"acceleration":3.0,"curvature":0,"holonomicRotation":180.0,"angularVelocity":0.0,"holonomicAngularVelocity":0.0},{"time":1.0032311250886643,"pose":{"rotation":{"radians":0.0},"translation":{"x":3.8297090355200005,"y":3.0}},"velocity":3.009693375265994,"acceleration":3.0,"curvature":0,"holonomicRotation":180.0,"angularVelocity":0.0,"holonomicAngularVelocity":0.0},{"time":1.0090671379843863,"pose":{"rotation":{"radians":0.0},"translation":{"x":3.8473247334400007,"y":3.0}},"velocity":3.02720141395316,"acceleration":3.000000000000038,"curvature":0,"holonomicRotation":180.0,"angularVelocity":0.0,"holonomicAngularVelocity":0.0},{"time":1.0148760187004784,"pose":{"rotation":{"radians":0.0},"translation":{"x":3.864960000000001,"y":3.0}},"velocity":3.0446280561014367,"acceleration":3.0000000000000764,"curvature":0,"holonomicRotation":180.0,"angularVelocity":0.0,"holonomicAngularVelocity":0.0},{"time":1.0206579846876558,"pose":{"rotation":{"radians":0.0},"translation":{"x":3.8826140825600004,"y":3.0}},"velocity":3.0619739540629687,"acceleration":2.999999999999962,"curvature":0,"holonomicRotation":180.0,"angularVelocity":0.0,"holonomicAngularVelocity":0.0},{"time":1.0264132463681481,"pose":{"rotation":{"radians":0.0},"translation":{"x":3.900286228480001,"y":3.0}},"velocity":3.0792397391044455,"acceleration":2.9999999999999614,"curvature":0,"holonomicRotation":180.0,"angularVelocity":0.0,"holonomicAngularVelocity":0.0},{"time":1.0321420073872265,"pose":{"rotation":{"radians":0.0},"translation":{"x":3.9179756851200005,"y":3.0}},"velocity":3.0964260221616806,"acceleration":3.0,"curvature":0,"holonomicRotation":180.0,"angularVelocity":0.0,"holonomicAngularVelocity":0.0},{"time":1.0378444648533165,"pose":{"rotation":{"radians":0.0},"translation":{"x":3.935681699840001,"y":3.0}},"velocity":3.1135333945599513,"acceleration":3.000000000000117,"curvature":0,"holonomicRotation":180.0,"angularVelocity":0.0,"holonomicAngularVelocity":0.0},{"time":1.0435208095673034,"pose":{"rotation":{"radians":0.0},"translation":{"x":3.953403520000001,"y":3.0}},"velocity":3.130562428701912,"acceleration":3.0,"curvature":0,"holonomicRotation":180.0,"angularVelocity":0.0,"holonomicAngularVelocity":0.0},{"time":1.0491712262416149,"pose":{"rotation":{"radians":0.0},"translation":{"x":3.971140392960001,"y":3.0}},"velocity":3.147513678724846,"acceleration":2.999999999999961,"curvature":0,"holonomicRotation":180.0,"angularVelocity":0.0,"holonomicAngularVelocity":0.0},{"time":1.0547958937096158,"pose":{"rotation":{"radians":0.0},"translation":{"x":3.988891566080001,"y":3.0}},"velocity":3.164387681128849,"acceleration":3.0,"curvature":0,"holonomicRotation":180.0,"angularVelocity":0.0,"holonomicAngularVelocity":0.0},{"time":1.0603949851258259,"pose":{"rotation":{"radians":0.0},"translation":{"x":4.006656286720001,"y":3.0}},"velocity":3.181184955377479,"acceleration":2.9999999999999605,"curvature":0,"holonomicRotation":180.0,"angularVelocity":0.0,"holonomicAngularVelocity":0.0},{"time":1.065968668157434,"pose":{"rotation":{"radians":0.0},"translation":{"x":4.024433802240001,"y":3.0}},"velocity":3.197906004472303,"acceleration":2.9999999999999205,"curvature":0,"holonomicRotation":180.0,"angularVelocity":0.0,"holonomicAngularVelocity":0.0},{"time":1.0715171051675596,"pose":{"rotation":{"radians":0.0},"translation":{"x":4.04222336,"y":3.0}},"velocity":3.2145513155026797,"acceleration":3.0,"curvature":0,"holonomicRotation":180.0,"angularVelocity":0.0,"holonomicAngularVelocity":0.0},{"time":1.0770404533906794,"pose":{"rotation":{"radians":0.0},"translation":{"x":4.060024207360001,"y":3.0}},"velocity":3.2311213601720397,"acceleration":3.0000000000000804,"curvature":0,"holonomicRotation":180.0,"angularVelocity":0.0,"holonomicAngularVelocity":0.0},{"time":1.082538865100618,"pose":{"rotation":{"radians":0.0},"translation":{"x":4.077835591680001,"y":3.0}},"velocity":3.2476165953018556,"acceleration":3.0000000000000404,"curvature":0,"holonomicRotation":180.0,"angularVelocity":0.0,"holonomicAngularVelocity":0.0},{"time":1.0880124877714719,"pose":{"rotation":{"radians":0.0},"translation":{"x":4.095656760320001,"y":3.0}},"velocity":3.2640374633144167,"acceleration":2.9999999999999187,"curvature":0,"holonomicRotation":180.0,"angularVelocity":0.0,"holonomicAngularVelocity":0.0},{"time":1.0934614642318223,"pose":{"rotation":{"radians":0.0},"translation":{"x":4.113486960640001,"y":3.0}},"velocity":3.280384392695468,"acceleration":2.999999999999959,"curvature":0,"holonomicRotation":180.0,"angularVelocity":0.0,"holonomicAngularVelocity":0.0},{"time":1.0988859328125615,"pose":{"rotation":{"radians":0.0},"translation":{"x":4.13132544,"y":3.0}},"velocity":3.2966577984376855,"acceleration":3.0,"curvature":0,"holonomicRotation":180.0,"angularVelocity":0.0,"holonomicAngularVelocity":0.0},{"time":1.104286027488652,"pose":{"rotation":{"radians":0.0},"translation":{"x":4.149171445760001,"y":3.0}},"velocity":3.312858082465956,"acceleration":2.999999999999918,"curvature":0,"holonomicRotation":180.0,"angularVelocity":0.0,"holonomicAngularVelocity":0.0},{"time":1.109661878015101,"pose":{"rotation":{"radians":0.0},"translation":{"x":4.167024225280001,"y":3.0}},"velocity":3.3289856340453037,"acceleration":3.0,"curvature":0,"holonomicRotation":180.0,"angularVelocity":0.0,"holonomicAngularVelocity":0.0},{"time":1.115013610057444,"pose":{"rotation":{"radians":0.0},"translation":{"x":4.1848830259200005,"y":3.0}},"velocity":3.3450408301723322,"acceleration":3.0,"curvature":0,"holonomicRotation":180.0,"angularVelocity":0.0,"holonomicAngularVelocity":0.0},{"time":1.120341345316983,"pose":{"rotation":{"radians":0.0},"translation":{"x":4.202747095040001,"y":3.0}},"velocity":3.3610240359509493,"acceleration":2.9999999999999583,"curvature":0,"holonomicRotation":180.0,"angularVelocity":0.0,"holonomicAngularVelocity":0.0},{"time":1.1256452016510354,"pose":{"rotation":{"radians":0.0},"translation":{"x":4.220615680000001,"y":3.0}},"velocity":3.3769356049531067,"acceleration":3.0000000000000417,"curvature":0,"holonomicRotation":180.0,"angularVelocity":0.0,"holonomicAngularVelocity":0.0},{"time":1.1309252931884288,"pose":{"rotation":{"radians":0.0},"translation":{"x":4.238488028160001,"y":3.0}},"velocity":3.3927758795652867,"acceleration":2.999999999999958,"curvature":0,"holonomicRotation":180.0,"angularVelocity":0.0,"holonomicAngularVelocity":0.0},{"time":1.1361817304404553,"pose":{"rotation":{"radians":0.0},"translation":{"x":4.256363386880001,"y":3.0}},"velocity":3.408545191321366,"acceleration":2.999999999999958,"curvature":0,"holonomicRotation":180.0,"angularVelocity":0.0,"holonomicAngularVelocity":0.0},{"time":1.1414146204075015,"pose":{"rotation":{"radians":0.0},"translation":{"x":4.274241003520001,"y":3.0}},"velocity":3.4242438612225046,"acceleration":3.0,"curvature":0,"holonomicRotation":180.0,"angularVelocity":0.0,"holonomicAngularVelocity":0.0},{"time":1.1466240666815493,"pose":{"rotation":{"radians":0.0},"translation":{"x":4.292120125440001,"y":3.0}},"velocity":3.439872200044648,"acceleration":3.0000000000000853,"curvature":0,"holonomicRotation":180.0,"angularVelocity":0.0,"holonomicAngularVelocity":0.0},{"time":1.1518101695447331,"pose":{"rotation":{"radians":0.0},"translation":{"x":4.3100000000000005,"y":3.0}},"velocity":3.4554305086342,"acceleration":3.0,"curvature":0,"holonomicRotation":180.0,"angularVelocity":0.0,"holonomicAngularVelocity":0.0},{"time":1.1569730260641344,"pose":{"rotation":{"radians":0.0},"translation":{"x":4.327879874560001,"y":3.0}},"velocity":3.470919078192404,"acceleration":3.000000000000043,"curvature":0,"holonomicRotation":180.0,"angularVelocity":0.0,"holonomicAngularVelocity":0.0},{"time":1.1621127301829774,"pose":{"rotation":{"radians":0.0},"translation":{"x":4.345758996480001,"y":3.0}},"velocity":3.486338190548933,"acceleration":3.0,"curvature":0,"holonomicRotation":180.0,"angularVelocity":0.0,"holonomicAngularVelocity":0.0},{"time":1.1672293728083898,"pose":{"rotation":{"radians":0.0},"translation":{"x":4.363636613120001,"y":3.0}},"velocity":3.50168811842517,"acceleration":2.9999999999999565,"curvature":0,"holonomicRotation":180.0,"angularVelocity":0.0,"holonomicAngularVelocity":0.0},{"time":1.1723230418958763,"pose":{"rotation":{"radians":0.0},"translation":{"x":4.381511971840001,"y":3.0}},"velocity":3.516969125687629,"acceleration":2.9999999999999565,"curvature":0,"holonomicRotation":180.0,"angularVelocity":0.0,"holonomicAngularVelocity":0.0},{"time":1.1773938225306493,"pose":{"rotation":{"radians":0.0},"translation":{"x":4.399384320000001,"y":3.0}},"velocity":3.532181467591948,"acceleration":2.999999999999956,"curvature":0,"holonomicRotation":180.0,"angularVelocity":0.0,"holonomicAngularVelocity":0.0},{"time":1.182441797005953,"pose":{"rotation":{"radians":0.0},"translation":{"x":4.417252904960002,"y":3.0}},"velocity":3.5473253910178593,"acceleration":3.0,"curvature":0,"holonomicRotation":180.0,"angularVelocity":0.0,"holonomicAngularVelocity":0.0},{"time":1.18746704489851,"pose":{"rotation":{"radians":0.0},"translation":{"x":4.4351169740800005,"y":3.0}},"velocity":3.56240113469553,"acceleration":3.0,"curvature":0,"holonomicRotation":180.0,"angularVelocity":0.0,"holonomicAngularVelocity":0.0},{"time":1.1924696431412136,"pose":{"rotation":{"radians":0.0},"translation":{"x":4.4529757747200005,"y":3.0}},"velocity":3.577408929423641,"acceleration":3.0,"curvature":0,"holonomicRotation":180.0,"angularVelocity":0.0,"holonomicAngularVelocity":0.0},{"time":1.1974496660931797,"pose":{"rotation":{"radians":0.0},"translation":{"x":4.4708285542400015,"y":3.0}},"velocity":3.592348998279539,"acceleration":2.9999999999999556,"curvature":0,"holonomicRotation":180.0,"angularVelocity":0.0,"holonomicAngularVelocity":0.0},{"time":1.2024071856072718,"pose":{"rotation":{"radians":0.0},"translation":{"x":4.488674560000001,"y":3.0}},"velocity":3.6072215568218153,"acceleration":3.000000000000045,"curvature":0,"holonomicRotation":180.0,"angularVelocity":0.0,"holonomicAngularVelocity":0.0},{"time":1.2073422710952078,"pose":{"rotation":{"radians":0.0},"translation":{"x":4.5065130393600015,"y":3.0}},"velocity":3.622026813285623,"acceleration":2.99999999999991,"curvature":0,"holonomicRotation":180.0,"angularVelocity":0.0,"holonomicAngularVelocity":0.0},{"time":1.2122549895903367,"pose":{"rotation":{"radians":0.0},"translation":{"x":4.524343239680001,"y":3.0}},"velocity":3.6367649687710095,"acceleration":2.9999999999999547,"curvature":0,"holonomicRotation":180.0,"angularVelocity":0.0,"holonomicAngularVelocity":0.0},{"time":1.2171454058081972,"pose":{"rotation":{"radians":0.0},"translation":{"x":4.5421644083200015,"y":3.0}},"velocity":3.6514362174245907,"acceleration":2.9999999999999547,"curvature":0,"holonomicRotation":180.0,"angularVelocity":0.0,"holonomicAngularVelocity":0.0},{"time":1.2220135822049336,"pose":{"rotation":{"radians":0.0},"translation":{"x":4.559975792640001,"y":3.0}},"velocity":3.6660407466148004,"acceleration":3.000000000000091,"curvature":0,"holonomicRotation":180.0,"angularVelocity":0.0,"holonomicAngularVelocity":0.0},{"time":1.2268595790336674,"pose":{"rotation":{"radians":0.0},"translation":{"x":4.5777766400000015,"y":3.0}},"velocity":3.6805787371010017,"acceleration":3.0,"curvature":0,"holonomicRotation":180.0,"angularVelocity":0.0,"holonomicAngularVelocity":0.0},{"time":1.2316834543988973,"pose":{"rotation":{"radians":0.0},"translation":{"x":4.595566197760001,"y":3.0}},"velocity":3.6950503631966916,"acceleration":3.000000000000046,"curvature":0,"holonomicRotation":180.0,"angularVelocity":0.0,"holonomicAngularVelocity":0.0},{"time":1.2364852643090145,"pose":{"rotation":{"radians":0.0},"translation":{"x":4.613343713280001,"y":3.0}},"velocity":3.7094557929270437,"acceleration":3.0000000000000924,"curvature":0,"holonomicRotation":180.0,"angularVelocity":0.0,"holonomicAngularVelocity":0.0},{"time":1.2412650627270017,"pose":{"rotation":{"radians":0.0},"translation":{"x":4.6311084339200015,"y":3.0}},"velocity":3.723795188181005,"acceleration":2.9999999999999534,"curvature":0,"holonomicRotation":180.0,"angularVelocity":0.0,"holonomicAngularVelocity":0.0},{"time":1.2460229016193887,"pose":{"rotation":{"radians":0.0},"translation":{"x":4.648859607040001,"y":3.0}},"velocity":3.738068704858166,"acceleration":2.9999999999999534,"curvature":0,"holonomicRotation":180.0,"angularVelocity":0.0,"holonomicAngularVelocity":0.0},{"time":1.2507588310035367,"pose":{"rotation":{"radians":0.0},"translation":{"x":4.666596480000001,"y":3.0}},"velocity":3.7522764930106103,"acceleration":3.0000000000000937,"curvature":0,"holonomicRotation":180.0,"angularVelocity":0.0,"holonomicAngularVelocity":0.0},{"time":1.2554728989933104,"pose":{"rotation":{"radians":0.0},"translation":{"x":4.684318300160001,"y":3.0}},"velocity":3.766418696979932,"acceleration":3.000000000000094,"curvature":0,"holonomicRotation":180.0,"angularVelocity":0.0,"holonomicAngularVelocity":0.0},{"time":1.260165151843202,"pose":{"rotation":{"radians":0.0},"translation":{"x":4.702024314880001,"y":3.0}},"velocity":3.7804954555296066,"acceleration":3.0,"curvature":0,"holonomicRotation":180.0,"angularVelocity":0.0,"holonomicAngularVelocity":0.0},{"time":1.2648356339909679,"pose":{"rotation":{"radians":0.0},"translation":{"x":4.719713771520001,"y":3.0}},"velocity":3.7945069019729045,"acceleration":3.0000000000000475,"curvature":0,"holonomicRotation":180.0,"angularVelocity":0.0,"holonomicAngularVelocity":0.0},{"time":1.2694843880988325,"pose":{"rotation":{"radians":0.0},"translation":{"x":4.737385917440001,"y":3.0}},"velocity":3.808453164296498,"acceleration":2.9999999999999045,"curvature":0,"holonomicRotation":180.0,"angularVelocity":0.0,"holonomicAngularVelocity":0.0},{"time":1.2741114550933137,"pose":{"rotation":{"radians":0.0},"translation":{"x":4.755040000000002,"y":3.0}},"velocity":3.822334365279941,"acceleration":2.999999999999904,"curvature":0,"holonomicRotation":180.0,"angularVelocity":0.0,"holonomicAngularVelocity":0.0},{"time":1.278716874203721,"pose":{"rotation":{"radians":0.0},"translation":{"x":4.772675266560002,"y":3.0}},"velocity":3.8361506226111626,"acceleration":2.9999999999999516,"curvature":0,"holonomicRotation":180.0,"angularVelocity":0.0,"holonomicAngularVelocity":0.0},{"time":1.283300682999377,"pose":{"rotation":{"radians":0.0},"translation":{"x":4.790290964480001,"y":3.0}},"velocity":3.849902048998131,"acceleration":3.000000000000097,"curvature":0,"holonomicRotation":180.0,"angularVelocity":0.0,"holonomicAngularVelocity":0.0},{"time":1.2878629174256089,"pose":{"rotation":{"radians":0.0},"translation":{"x":4.8078863411200015,"y":3.0}},"velocity":3.863588752276827,"acceleration":3.000000000000049,"curvature":0,"holonomicRotation":180.0,"angularVelocity":0.0,"holonomicAngularVelocity":0.0},{"time":1.2924036118385518,"pose":{"rotation":{"radians":0.0},"translation":{"x":4.825460643840001,"y":3.0}},"velocity":3.8772108355156556,"acceleration":2.999999999999951,"curvature":0,"holonomicRotation":180.0,"angularVelocity":0.0,"holonomicAngularVelocity":0.0},{"time":1.2969227990388121,"pose":{"rotation":{"radians":0.0},"translation":{"x":4.843013120000001,"y":3.0}},"velocity":3.8907683971164366,"acceleration":3.0,"curvature":0,"holonomicRotation":180.0,"angularVelocity":0.0,"holonomicAngularVelocity":0.0},{"time":1.3014205103040295,"pose":{"rotation":{"radians":0.0},"translation":{"x":4.860543016960001,"y":3.0}},"velocity":3.9042615309120885,"acceleration":2.9999999999999507,"curvature":0,"holonomicRotation":180.0,"angularVelocity":0.0,"holonomicAngularVelocity":0.0},{"time":1.3058967754203752,"pose":{"rotation":{"radians":0.0},"translation":{"x":4.878049582080001,"y":3.0}},"velocity":3.9176903262611256,"acceleration":3.0,"curvature":0,"holonomicRotation":180.0,"angularVelocity":0.0,"holonomicAngularVelocity":0.0},{"time":1.3103516227130287,"pose":{"rotation":{"radians":0.0},"translation":{"x":4.895532062720002,"y":3.0}},"velocity":3.9310548681390864,"acceleration":3.0000000000000497,"curvature":0,"holonomicRotation":180.0,"angularVelocity":0.0,"holonomicAngularVelocity":0.0},{"time":1.314785079075664,"pose":{"rotation":{"radians":0.0},"translation":{"x":4.912989706240001,"y":3.0}},"velocity":3.944355237226993,"acceleration":3.0000000000001004,"curvature":0,"holonomicRotation":180.0,"angularVelocity":0.0,"holonomicAngularVelocity":0.0},{"time":1.3191971699989862,"pose":{"rotation":{"radians":0.0},"translation":{"x":4.9304217600000015,"y":3.0}},"velocity":3.957591509996959,"acceleration":3.0,"curvature":0,"holonomicRotation":180.0,"angularVelocity":0.0,"holonomicAngularVelocity":0.0},{"time":1.323587919598342,"pose":{"rotation":{"radians":0.0},"translation":{"x":4.947827471360001,"y":3.0}},"velocity":3.9707637587950266,"acceleration":3.0,"curvature":0,"holonomicRotation":180.0,"angularVelocity":0.0,"holonomicAngularVelocity":0.0},{"time":1.327957350640449,"pose":{"rotation":{"radians":0.0},"translation":{"x":4.965206087680001,"y":3.0}},"velocity":3.9838720519213475,"acceleration":3.0,"curvature":0,"holonomicRotation":180.0,"angularVelocity":0.0,"holonomicAngularVelocity":0.0},{"time":1.332305484569261,"pose":{"rotation":{"radians":0.0},"translation":{"x":4.982556856320001,"y":3.0}},"velocity":3.996916453707784,"acceleration":3.000000000000051,"curvature":0,"holonomicRotation":180.0,"angularVelocity":0.0,"holonomicAngularVelocity":0.0},{"time":1.3366376964712545,"pose":{"rotation":{"radians":0.0},"translation":{"x":4.999879024640002,"y":3.0}},"velocity":4.0,"acceleration":0.7117718066369636,"curvature":0,"holonomicRotation":180.0,"angularVelocity":0.0,"holonomicAngularVelocity":0.0},{"time":1.3409609003112544,"pose":{"rotation":{"radians":0.0},"translation":{"x":5.017171840000001,"y":3.0}},"velocity":4.0,"acceleration":0.0,"curvature":0,"holonomicRotation":180.0,"angularVelocity":0.0,"holonomicAngularVelocity":0.0},{"time":1.3452765777512543,"pose":{"rotation":{"radians":0.0},"translation":{"x":5.034434549760001,"y":3.0}},"velocity":4.0,"acceleration":0.0,"curvature":0,"holonomicRotation":180.0,"angularVelocity":0.0,"holonomicAngularVelocity":0.0},{"time":1.3495845406312543,"pose":{"rotation":{"radians":0.0},"translation":{"x":5.051666401280001,"y":3.0}},"velocity":4.0,"acceleration":0.0,"curvature":0,"holonomicRotation":180.0,"angularVelocity":0.0,"holonomicAngularVelocity":0.0},{"time":1.3538846007912544,"pose":{"rotation":{"radians":0.0},"translation":{"x":5.0688666419200015,"y":3.0}},"velocity":4.0,"acceleration":0.0,"curvature":0,"holonomicRotation":180.0,"angularVelocity":0.0,"holonomicAngularVelocity":0.0},{"time":1.3581765700712545,"pose":{"rotation":{"radians":0.0},"translation":{"x":5.086034519040002,"y":3.0}},"velocity":4.0,"acceleration":0.0,"curvature":0,"holonomicRotation":180.0,"angularVelocity":0.0,"holonomicAngularVelocity":0.0},{"time":1.3624602603112543,"pose":{"rotation":{"radians":0.0},"translation":{"x":5.103169280000001,"y":3.0}},"velocity":4.0,"acceleration":0.0,"curvature":0,"holonomicRotation":180.0,"angularVelocity":0.0,"holonomicAngularVelocity":0.0},{"time":1.3667354833512544,"pose":{"rotation":{"radians":0.0},"translation":{"x":5.1202701721600015,"y":3.0}},"velocity":4.0,"acceleration":0.0,"curvature":0,"holonomicRotation":180.0,"angularVelocity":0.0,"holonomicAngularVelocity":0.0},{"time":1.3710020510312544,"pose":{"rotation":{"radians":0.0},"translation":{"x":5.1373364428800015,"y":3.0}},"velocity":4.0,"acceleration":0.0,"curvature":0,"holonomicRotation":180.0,"angularVelocity":0.0,"holonomicAngularVelocity":0.0},{"time":1.3752597751912543,"pose":{"rotation":{"radians":0.0},"translation":{"x":5.154367339520001,"y":3.0}},"velocity":4.0,"acceleration":0.0,"curvature":0,"holonomicRotation":180.0,"angularVelocity":0.0,"holonomicAngularVelocity":0.0},{"time":1.3795084676712546,"pose":{"rotation":{"radians":0.0},"translation":{"x":5.171362109440002,"y":3.0}},"velocity":4.0,"acceleration":0.0,"curvature":0,"holonomicRotation":180.0,"angularVelocity":0.0,"holonomicAngularVelocity":0.0},{"time":1.3837479403112543,"pose":{"rotation":{"radians":0.0},"translation":{"x":5.188320000000001,"y":3.0}},"velocity":4.0,"acceleration":0.0,"curvature":0,"holonomicRotation":180.0,"angularVelocity":0.0,"holonomicAngularVelocity":0.0},{"time":1.3879780049512545,"pose":{"rotation":{"radians":0.0},"translation":{"x":5.205240258560002,"y":3.0}},"velocity":4.0,"acceleration":0.0,"curvature":0,"holonomicRotation":180.0,"angularVelocity":0.0,"holonomicAngularVelocity":0.0},{"time":1.3921984734312545,"pose":{"rotation":{"radians":0.0},"translation":{"x":5.222122132480002,"y":3.0}},"velocity":4.0,"acceleration":0.0,"curvature":0,"holonomicRotation":180.0,"angularVelocity":0.0,"holonomicAngularVelocity":0.0},{"time":1.3964091575912545,"pose":{"rotation":{"radians":0.0},"translation":{"x":5.238964869120002,"y":3.0}},"velocity":4.0,"acceleration":0.0,"curvature":0,"holonomicRotation":180.0,"angularVelocity":0.0,"holonomicAngularVelocity":0.0},{"time":1.4006098692712545,"pose":{"rotation":{"radians":0.0},"translation":{"x":5.255767715840002,"y":3.0}},"velocity":4.0,"acceleration":0.0,"curvature":0,"holonomicRotation":180.0,"angularVelocity":0.0,"holonomicAngularVelocity":0.0},{"time":1.4048004203112543,"pose":{"rotation":{"radians":0.0},"translation":{"x":5.272529920000001,"y":3.0}},"velocity":4.0,"acceleration":0.0,"curvature":0,"holonomicRotation":180.0,"angularVelocity":0.0,"holonomicAngularVelocity":0.0},{"time":1.4089806225512544,"pose":{"rotation":{"radians":0.0},"translation":{"x":5.289250728960002,"y":3.0}},"velocity":4.0,"acceleration":0.0,"curvature":0,"holonomicRotation":180.0,"angularVelocity":0.0,"holonomicAngularVelocity":0.0},{"time":1.4131502878312545,"pose":{"rotation":{"radians":0.0},"translation":{"x":5.305929390080002,"y":3.0}},"velocity":4.0,"acceleration":0.0,"curvature":0,"holonomicRotation":180.0,"angularVelocity":0.0,"holonomicAngularVelocity":0.0},{"time":1.4173092279912545,"pose":{"rotation":{"radians":0.0},"translation":{"x":5.322565150720002,"y":3.0}},"velocity":4.0,"acceleration":0.0,"curvature":0,"holonomicRotation":180.0,"angularVelocity":0.0,"holonomicAngularVelocity":0.0},{"time":1.4214572548712545,"pose":{"rotation":{"radians":0.0},"translation":{"x":5.339157258240002,"y":3.0}},"velocity":4.0,"acceleration":0.0,"curvature":0,"holonomicRotation":180.0,"angularVelocity":0.0,"holonomicAngularVelocity":0.0},{"time":1.4255941803112546,"pose":{"rotation":{"radians":0.0},"translation":{"x":5.355704960000002,"y":3.0}},"velocity":4.0,"acceleration":0.0,"curvature":0,"holonomicRotation":180.0,"angularVelocity":0.0,"holonomicAngularVelocity":0.0},{"time":1.4297198161512545,"pose":{"rotation":{"radians":0.0},"translation":{"x":5.372207503360002,"y":3.0}},"velocity":4.0,"acceleration":0.0,"curvature":0,"holonomicRotation":180.0,"angularVelocity":0.0,"holonomicAngularVelocity":0.0},{"time":1.4338339742312542,"pose":{"rotation":{"radians":0.0},"translation":{"x":5.388664135680001,"y":3.0}},"velocity":4.0,"acceleration":0.0,"curvature":0,"holonomicRotation":180.0,"angularVelocity":0.0,"holonomicAngularVelocity":0.0},{"time":1.4379364663912544,"pose":{"rotation":{"radians":0.0},"translation":{"x":5.4050741043200015,"y":3.0}},"velocity":4.0,"acceleration":0.0,"curvature":0,"holonomicRotation":180.0,"angularVelocity":0.0,"holonomicAngularVelocity":0.0},{"time":1.4420271044712545,"pose":{"rotation":{"radians":0.0},"translation":{"x":5.421436656640002,"y":3.0}},"velocity":4.0,"acceleration":0.0,"curvature":0,"holonomicRotation":180.0,"angularVelocity":0.0,"holonomicAngularVelocity":0.0},{"time":1.4461057003112545,"pose":{"rotation":{"radians":0.0},"translation":{"x":5.437751040000002,"y":3.0}},"velocity":4.0,"acceleration":0.0,"curvature":0,"holonomicRotation":180.0,"angularVelocity":0.0,"holonomicAngularVelocity":0.0},{"time":1.4501720657512545,"pose":{"rotation":{"radians":0.0},"translation":{"x":5.454016501760002,"y":3.0}},"velocity":4.0,"acceleration":0.0,"curvature":0,"holonomicRotation":180.0,"angularVelocity":0.0,"holonomicAngularVelocity":0.0},{"time":1.4542260126312545,"pose":{"rotation":{"radians":0.0},"translation":{"x":5.470232289280002,"y":3.0}},"velocity":4.0,"acceleration":0.0,"curvature":0,"holonomicRotation":180.0,"angularVelocity":0.0,"holonomicAngularVelocity":0.0},{"time":1.4582673527912546,"pose":{"rotation":{"radians":0.0},"translation":{"x":5.4863976499200025,"y":3.0}},"velocity":4.0,"acceleration":0.0,"curvature":0,"holonomicRotation":180.0,"angularVelocity":0.0,"holonomicAngularVelocity":0.0},{"time":1.4622958980712544,"pose":{"rotation":{"radians":0.0},"translation":{"x":5.502511831040001,"y":3.0}},"velocity":4.0,"acceleration":0.0,"curvature":0,"holonomicRotation":180.0,"angularVelocity":0.0,"holonomicAngularVelocity":0.0},{"time":1.4663114603112544,"pose":{"rotation":{"radians":0.0},"translation":{"x":5.518574080000001,"y":3.0}},"velocity":4.0,"acceleration":0.0,"curvature":0,"holonomicRotation":180.0,"angularVelocity":0.0,"holonomicAngularVelocity":0.0},{"time":1.4703138513512544,"pose":{"rotation":{"radians":0.0},"translation":{"x":5.534583644160001,"y":3.0}},"velocity":4.0,"acceleration":0.0,"curvature":0,"holonomicRotation":180.0,"angularVelocity":0.0,"holonomicAngularVelocity":0.0},{"time":1.4743028830312543,"pose":{"rotation":{"radians":0.0},"translation":{"x":5.550539770880001,"y":3.0}},"velocity":4.0,"acceleration":0.0,"curvature":0,"holonomicRotation":180.0,"angularVelocity":0.0,"holonomicAngularVelocity":0.0},{"time":1.4782783671912547,"pose":{"rotation":{"radians":0.0},"translation":{"x":5.566441707520003,"y":3.0}},"velocity":4.0,"acceleration":0.0,"curvature":0,"holonomicRotation":180.0,"angularVelocity":0.0,"holonomicAngularVelocity":0.0},{"time":1.4822401156712544,"pose":{"rotation":{"radians":0.0},"translation":{"x":5.582288701440001,"y":3.0}},"velocity":4.0,"acceleration":0.0,"curvature":0,"holonomicRotation":180.0,"angularVelocity":0.0,"holonomicAngularVelocity":0.0},{"time":1.4861879403112546,"pose":{"rotation":{"radians":0.0},"translation":{"x":5.598080000000002,"y":3.0}},"velocity":4.0,"acceleration":0.0,"curvature":0,"holonomicRotation":180.0,"angularVelocity":0.0,"holonomicAngularVelocity":0.0},{"time":1.4901216529512544,"pose":{"rotation":{"radians":0.0},"translation":{"x":5.613814850560002,"y":3.0}},"velocity":4.0,"acceleration":0.0,"curvature":0,"holonomicRotation":180.0,"angularVelocity":0.0,"holonomicAngularVelocity":0.0},{"time":1.4940410654312546,"pose":{"rotation":{"radians":0.0},"translation":{"x":5.629492500480002,"y":3.0}},"velocity":4.0,"acceleration":0.0,"curvature":0,"holonomicRotation":180.0,"angularVelocity":0.0,"holonomicAngularVelocity":0.0},{"time":1.4979459895912546,"pose":{"rotation":{"radians":0.0},"translation":{"x":5.645112197120002,"y":3.0}},"velocity":4.0,"acceleration":0.0,"curvature":0,"holonomicRotation":180.0,"angularVelocity":0.0,"holonomicAngularVelocity":0.0},{"time":1.5018362372712546,"pose":{"rotation":{"radians":0.0},"translation":{"x":5.660673187840002,"y":3.0}},"velocity":4.0,"acceleration":0.0,"curvature":0,"holonomicRotation":180.0,"angularVelocity":0.0,"holonomicAngularVelocity":0.0},{"time":1.5057116203112546,"pose":{"rotation":{"radians":0.0},"translation":{"x":5.676174720000002,"y":3.0}},"velocity":4.0,"acceleration":0.0,"curvature":0,"holonomicRotation":180.0,"angularVelocity":0.0,"holonomicAngularVelocity":0.0},{"time":1.5095719505512546,"pose":{"rotation":{"radians":0.0},"translation":{"x":5.691616040960002,"y":3.0}},"velocity":4.0,"acceleration":0.0,"curvature":0,"holonomicRotation":180.0,"angularVelocity":0.0,"holonomicAngularVelocity":0.0},{"time":1.5134170398312545,"pose":{"rotation":{"radians":0.0},"translation":{"x":5.706996398080002,"y":3.0}},"velocity":4.0,"acceleration":0.0,"curvature":0,"holonomicRotation":180.0,"angularVelocity":0.0,"holonomicAngularVelocity":0.0},{"time":1.5172466999912544,"pose":{"rotation":{"radians":0.0},"translation":{"x":5.7223150387200015,"y":3.0}},"velocity":4.0,"acceleration":0.0,"curvature":0,"holonomicRotation":180.0,"angularVelocity":0.0,"holonomicAngularVelocity":0.0},{"time":1.5210607428712546,"pose":{"rotation":{"radians":0.0},"translation":{"x":5.737571210240002,"y":3.0}},"velocity":4.0,"acceleration":0.0,"curvature":0,"holonomicRotation":180.0,"angularVelocity":0.0,"holonomicAngularVelocity":0.0},{"time":1.5248589803112544,"pose":{"rotation":{"radians":0.0},"translation":{"x":5.752764160000002,"y":3.0}},"velocity":4.0,"acceleration":0.0,"curvature":0,"holonomicRotation":180.0,"angularVelocity":0.0,"holonomicAngularVelocity":0.0},{"time":1.5286412241512544,"pose":{"rotation":{"radians":0.0},"translation":{"x":5.767893135360001,"y":3.0}},"velocity":4.0,"acceleration":0.0,"curvature":0,"holonomicRotation":180.0,"angularVelocity":0.0,"holonomicAngularVelocity":0.0},{"time":1.5324072862312546,"pose":{"rotation":{"radians":0.0},"translation":{"x":5.782957383680002,"y":3.0}},"velocity":4.0,"acceleration":0.0,"curvature":0,"holonomicRotation":180.0,"angularVelocity":0.0,"holonomicAngularVelocity":0.0},{"time":1.5361569783912543,"pose":{"rotation":{"radians":0.0},"translation":{"x":5.797956152320001,"y":3.0}},"velocity":4.0,"acceleration":0.0,"curvature":0,"holonomicRotation":180.0,"angularVelocity":0.0,"holonomicAngularVelocity":0.0},{"time":1.5398901124712545,"pose":{"rotation":{"radians":0.0},"translation":{"x":5.812888688640002,"y":3.0}},"velocity":4.0,"acceleration":0.0,"curvature":0,"holonomicRotation":180.0,"angularVelocity":0.0,"holonomicAngularVelocity":0.0},{"time":1.5436065003112545,"pose":{"rotation":{"radians":0.0},"translation":{"x":5.827754240000002,"y":3.0}},"velocity":4.0,"acceleration":0.0,"curvature":0,"holonomicRotation":180.0,"angularVelocity":0.0,"holonomicAngularVelocity":0.0},{"time":1.5473059537512546,"pose":{"rotation":{"radians":0.0},"translation":{"x":5.842552053760002,"y":3.0}},"velocity":4.0,"acceleration":0.0,"curvature":0,"holonomicRotation":180.0,"angularVelocity":0.0,"holonomicAngularVelocity":0.0},{"time":1.5509882846312544,"pose":{"rotation":{"radians":0.0},"translation":{"x":5.857281377280001,"y":3.0}},"velocity":4.0,"acceleration":0.0,"curvature":0,"holonomicRotation":180.0,"angularVelocity":0.0,"holonomicAngularVelocity":0.0},{"time":1.5546533047912547,"pose":{"rotation":{"radians":0.0},"translation":{"x":5.871941457920003,"y":3.0}},"velocity":4.0,"acceleration":0.0,"curvature":0,"holonomicRotation":180.0,"angularVelocity":0.0,"holonomicAngularVelocity":0.0},{"time":1.5583008260712545,"pose":{"rotation":{"radians":0.0},"translation":{"x":5.886531543040002,"y":3.0}},"velocity":4.0,"acceleration":0.0,"curvature":0,"holonomicRotation":180.0,"angularVelocity":0.0,"holonomicAngularVelocity":0.0},{"time":1.5619306603112546,"pose":{"rotation":{"radians":0.0},"translation":{"x":5.901050880000002,"y":3.0}},"velocity":4.0,"acceleration":0.0,"curvature":0,"holonomicRotation":180.0,"angularVelocity":0.0,"holonomicAngularVelocity":0.0},{"time":1.5655426193512545,"pose":{"rotation":{"radians":0.0},"translation":{"x":5.915498716160002,"y":3.0}},"velocity":4.0,"acceleration":0.0,"curvature":0,"holonomicRotation":180.0,"angularVelocity":0.0,"holonomicAngularVelocity":0.0},{"time":1.5691365150312546,"pose":{"rotation":{"radians":0.0},"translation":{"x":5.929874298880002,"y":3.0}},"velocity":4.0,"acceleration":0.0,"curvature":0,"holonomicRotation":180.0,"angularVelocity":0.0,"holonomicAngularVelocity":0.0},{"time":1.5727121591912545,"pose":{"rotation":{"radians":0.0},"translation":{"x":5.944176875520002,"y":3.0}},"velocity":4.0,"acceleration":0.0,"curvature":0,"holonomicRotation":180.0,"angularVelocity":0.0,"holonomicAngularVelocity":0.0},{"time":1.5762693636712546,"pose":{"rotation":{"radians":0.0},"translation":{"x":5.958405693440002,"y":3.0}},"velocity":4.0,"acceleration":0.0,"curvature":0,"holonomicRotation":180.0,"angularVelocity":0.0,"holonomicAngularVelocity":0.0},{"time":1.5798079403112546,"pose":{"rotation":{"radians":0.0},"translation":{"x":5.972560000000002,"y":3.0}},"velocity":4.0,"acceleration":0.0,"curvature":0,"holonomicRotation":180.0,"angularVelocity":0.0,"holonomicAngularVelocity":0.0},{"time":1.5833277009512547,"pose":{"rotation":{"radians":0.0},"translation":{"x":5.986639042560003,"y":3.0}},"velocity":4.0,"acceleration":0.0,"curvature":0,"holonomicRotation":180.0,"angularVelocity":0.0,"holonomicAngularVelocity":0.0},{"time":1.5868284574312546,"pose":{"rotation":{"radians":0.0},"translation":{"x":6.000642068480002,"y":3.0}},"velocity":4.0,"acceleration":0.0,"curvature":0,"holonomicRotation":180.0,"angularVelocity":0.0,"holonomicAngularVelocity":0.0},{"time":1.5903100215912547,"pose":{"rotation":{"radians":0.0},"translation":{"x":6.014568325120003,"y":3.0}},"velocity":4.0,"acceleration":0.0,"curvature":0,"holonomicRotation":180.0,"angularVelocity":0.0,"holonomicAngularVelocity":0.0},{"time":1.5937722052712546,"pose":{"rotation":{"radians":0.0},"translation":{"x":6.028417059840002,"y":3.0}},"velocity":4.0,"acceleration":0.0,"curvature":0,"holonomicRotation":180.0,"angularVelocity":0.0,"holonomicAngularVelocity":0.0},{"time":1.5972148203112546,"pose":{"rotation":{"radians":0.0},"translation":{"x":6.042187520000002,"y":3.0}},"velocity":4.0,"acceleration":0.0,"curvature":0,"holonomicRotation":180.0,"angularVelocity":0.0,"holonomicAngularVelocity":0.0},{"time":1.6006376785512546,"pose":{"rotation":{"radians":0.0},"translation":{"x":6.055878952960002,"y":3.0}},"velocity":4.0,"acceleration":0.0,"curvature":0,"holonomicRotation":180.0,"angularVelocity":0.0,"holonomicAngularVelocity":0.0},{"time":1.6040405918312546,"pose":{"rotation":{"radians":0.0},"translation":{"x":6.069490606080002,"y":3.0}},"velocity":4.0,"acceleration":0.0,"curvature":0,"holonomicRotation":180.0,"angularVelocity":0.0,"holonomicAngularVelocity":0.0},{"time":1.6074233719912545,"pose":{"rotation":{"radians":0.0},"translation":{"x":6.083021726720002,"y":3.0}},"velocity":4.0,"acceleration":0.0,"curvature":0,"holonomicRotation":180.0,"angularVelocity":0.0,"holonomicAngularVelocity":0.0},{"time":1.6107858308712546,"pose":{"rotation":{"radians":0.0},"translation":{"x":6.096471562240002,"y":3.0}},"velocity":4.0,"acceleration":0.0,"curvature":0,"holonomicRotation":180.0,"angularVelocity":0.0,"holonomicAngularVelocity":0.0},{"time":1.6141277803112546,"pose":{"rotation":{"radians":0.0},"translation":{"x":6.109839360000002,"y":3.0}},"velocity":4.0,"acceleration":0.0,"curvature":0,"holonomicRotation":180.0,"angularVelocity":0.0,"holonomicAngularVelocity":0.0},{"time":1.6174490321512547,"pose":{"rotation":{"radians":0.0},"translation":{"x":6.123124367360003,"y":3.0}},"velocity":4.0,"acceleration":0.0,"curvature":0,"holonomicRotation":180.0,"angularVelocity":0.0,"holonomicAngularVelocity":0.0},{"time":1.6207493982312544,"pose":{"rotation":{"radians":0.0},"translation":{"x":6.136325831680002,"y":3.0}},"velocity":4.0,"acceleration":0.0,"curvature":0,"holonomicRotation":180.0,"angularVelocity":0.0,"holonomicAngularVelocity":0.0},{"time":1.6240286903912546,"pose":{"rotation":{"radians":0.0},"translation":{"x":6.1494430003200025,"y":3.0}},"velocity":4.0,"acceleration":0.0,"curvature":0,"holonomicRotation":180.0,"angularVelocity":0.0,"holonomicAngularVelocity":0.0},{"time":1.6272867204712544,"pose":{"rotation":{"radians":0.0},"translation":{"x":6.162475120640002,"y":3.0}},"velocity":4.0,"acceleration":0.0,"curvature":0,"holonomicRotation":180.0,"angularVelocity":0.0,"holonomicAngularVelocity":0.0},{"time":1.6305233003112547,"pose":{"rotation":{"radians":0.0},"translation":{"x":6.175421440000003,"y":3.0}},"velocity":4.0,"acceleration":0.0,"curvature":0,"holonomicRotation":180.0,"angularVelocity":0.0,"holonomicAngularVelocity":0.0},{"time":1.6337382417512545,"pose":{"rotation":{"radians":0.0},"translation":{"x":6.188281205760002,"y":3.0}},"velocity":4.0,"acceleration":0.0,"curvature":0,"holonomicRotation":180.0,"angularVelocity":0.0,"holonomicAngularVelocity":0.0},{"time":1.6369313566312544,"pose":{"rotation":{"radians":0.0},"translation":{"x":6.201053665280002,"y":3.0}},"velocity":4.0,"acceleration":0.0,"curvature":0,"holonomicRotation":180.0,"angularVelocity":0.0,"holonomicAngularVelocity":0.0},{"time":1.6401024567912545,"pose":{"rotation":{"radians":0.0},"translation":{"x":6.213738065920002,"y":3.0}},"velocity":4.0,"acceleration":0.0,"curvature":0,"holonomicRotation":180.0,"angularVelocity":0.0,"holonomicAngularVelocity":0.0},{"time":1.6432513540712546,"pose":{"rotation":{"radians":0.0},"translation":{"x":6.226333655040002,"y":3.0}},"velocity":4.0,"acceleration":0.0,"curvature":0,"holonomicRotation":180.0,"angularVelocity":0.0,"holonomicAngularVelocity":0.0},{"time":1.6463778603112544,"pose":{"rotation":{"radians":0.0},"translation":{"x":6.238839680000002,"y":3.0}},"velocity":4.0,"acceleration":0.0,"curvature":0,"holonomicRotation":180.0,"angularVelocity":0.0,"holonomicAngularVelocity":0.0},{"time":1.6494817873512546,"pose":{"rotation":{"radians":0.0},"translation":{"x":6.251255388160002,"y":3.0}},"velocity":4.0,"acceleration":0.0,"curvature":0,"holonomicRotation":180.0,"angularVelocity":0.0,"holonomicAngularVelocity":0.0},{"time":1.6525629470312546,"pose":{"rotation":{"radians":0.0},"translation":{"x":6.263580026880002,"y":3.0}},"velocity":4.0,"acceleration":0.0,"curvature":0,"holonomicRotation":180.0,"angularVelocity":0.0,"holonomicAngularVelocity":0.0},{"time":1.6556211511912546,"pose":{"rotation":{"radians":0.0},"translation":{"x":6.2758128435200025,"y":3.0}},"velocity":4.0,"acceleration":0.0,"curvature":0,"holonomicRotation":180.0,"angularVelocity":0.0,"holonomicAngularVelocity":0.0},{"time":1.6586562116712544,"pose":{"rotation":{"radians":0.0},"translation":{"x":6.287953085440002,"y":3.0}},"velocity":4.0,"acceleration":0.0,"curvature":0,"holonomicRotation":180.0,"angularVelocity":0.0,"holonomicAngularVelocity":0.0}]